{"OUTPUT": [{"TITLE": "Services details TREX_NIS", "DATA": [{"RESULT": "Error occured while fetching services data"}]}, {"TITLE": "Summary overview data TREX_NIS", "DATA": [{"RESULT": "Error occured while fetching summary data"}]}, {"TITLE": "Trace files TREX_NIS", "DATA": [{"RESULT": "Error occured while fetching trace files data"}]}, {"TITLE": "Ini files TREX_NIS", "DATA": [{"RESULT": "Error occured while fetching ini files data"}]}, {"TITLE": "Alert details TREX_NIS", "DATA": [{"RESULT": "Error occured while fetching alerts data"}]}, {"TITLE": "RFC - Connection test TREX_NIS", "DATA": [{"RESULT": "TREX_RFC_CONNECTION_CHECK: read failure DEST_RFC_TCPIP_READ"}]}, {"TITLE": "Version details TREX_NIS", "DATA": [{"RESULT": "Error occured while fetching version data"}]}]}